torchFunctions/__init__.py
torchFunctions/parameters.py
torchFunctions-0.0.3.dist-info/LICENSE
torchFunctions-0.0.3.dist-info/METADATA
torchFunctions-0.0.3.dist-info/WHEEL
torchFunctions-0.0.3.dist-info/top_level.txt
torchFunctions-0.0.3.dist-info/RECORD
