Metadata-Version: 2.1
Name: torchFunctions
Version: 0.0.3
Summary: This package makes the ease of using code in pytorch which needs to be used multiple times 
Home-page: https://github.com/Karthik-VG/torchFunctions
Author: Karthik-VG
Author-email: karthikvg.engineer@gmail.com
License: UNKNOWN
Project-URL: Bug Tracker, https://github.com/{USER_NAME}/{PROJECT_NAME}/issues
Platform: UNKNOWN
Classifier: Programming Language :: Python :: 3
Classifier: License :: OSI Approved :: MIT License
Classifier: Operating System :: OS Independent
Requires-Python: >=3.6
License-File: LICENSE
Requires-Dist: pymongo (==4.0.2)
Requires-Dist: pandas
Requires-Dist: torch
